odoo/addons/web_calendar_slot_duration/README.rst
odoo/addons/web_calendar_slot_duration/__init__.py
odoo/addons/web_calendar_slot_duration/__manifest__.py
odoo/addons/web_calendar_slot_duration/i18n/de.po
odoo/addons/web_calendar_slot_duration/i18n/pt_BR.po
odoo/addons/web_calendar_slot_duration/i18n/web_calendar_slot_duration.pot
odoo/addons/web_calendar_slot_duration/readme/CONFIGURE.rst
odoo/addons/web_calendar_slot_duration/readme/DESCRIPTION.rst
odoo/addons/web_calendar_slot_duration/readme/ROADMAP.rst
odoo/addons/web_calendar_slot_duration/readme/USAGE.rst
odoo/addons/web_calendar_slot_duration/static/description/icon.png
odoo/addons/web_calendar_slot_duration/static/description/index.html
odoo/addons/web_calendar_slot_duration/static/src/js/calendar_model.js
odoo/addons/web_calendar_slot_duration/templates/assets.xml
odoo14_addon_web_calendar_slot_duration-14.0.1.0.1.dev5.dist-info/METADATA
odoo14_addon_web_calendar_slot_duration-14.0.1.0.1.dev5.dist-info/WHEEL
odoo14_addon_web_calendar_slot_duration-14.0.1.0.1.dev5.dist-info/top_level.txt
odoo14_addon_web_calendar_slot_duration-14.0.1.0.1.dev5.dist-info/RECORD
